CandyLLM/__init__.py
CandyLLM/hub.py
CandyLLM-0.0.6.dist-info/LICENSE
CandyLLM-0.0.6.dist-info/METADATA
CandyLLM-0.0.6.dist-info/WHEEL
CandyLLM-0.0.6.dist-info/top_level.txt
CandyLLM-0.0.6.dist-info/RECORD
