Metadata-Version: 2.1
Name: CandyLLM
Version: 0.0.6
Summary: CandyLLM: Unified framework for HuggingFace and OpenAI Text-generation Models
Home-page: https://github.com/shreyanmitra/llm-wrapper
Author: Shreyan Mitra
Keywords: llms transformers mistral llama falcon gpt-4 alpaca
License-File: LICENSE
Requires-Dist: huggingface-hub
Requires-Dist: accelerate
Requires-Dist: openai
Requires-Dist: transformers
Requires-Dist: torch
Requires-Dist: llm-guard
Requires-Dist: gradio
